{
  "slug": "hrp",
  "name": "Hierarchical Risk Parity",
  "category": "C_RiskStructured",
  "method": "hrp",
  "weights": {
    "kr-large-cap": 0.13751504750972668,
    "kr-dividend": 0.13751428068822688,
    "us-large-cap": 0.13757630486517353,
    "us-tech": 0.13739436358232196,
    "kr-treasuries-10y": 0.08632332040109615,
    "us-treasuries-10y": 0.08237321461138569,
    "us-ig-credit": 0.0813034619912326,
    "gold": 0.14999999656775595,
    "kofr-cash": 0.05000000978308057,
    "money-market": 0.0
  },
  "expected_return": 0.05704541886284726,
  "expected_vol": 0.08886677390394868,
  "metrics": {
    "ex_ante_vol": 0.08886677390394868,
    "ex_ante_var95": -0.08914042420914833,
    "backtest_sharpe": 2.443029037866158,
    "backtest_vol": 0.10885586930558012,
    "backtest_maxdd": -0.07861574589711162,
    "hhi": 0.12147233150022774,
    "effective_n": 8.23232737570469,
    "top3": 0.4250913489426562,
    "ips_compliance": 0.9,
    "ips_flags": [
      "tracking_error=8.15% exceeds budget 6.00%"
    ],
    "tracking_error": 0.08145790219256192,
    "factor_tilts": {
      "growth": 0.46260692362419986,
      "rates": -0.762485699745612,
      "inflation": -0.3436672166753019,
      "dollar": 0.0
    },
    "diversification": 0.3611230454033424,
    "regime_fit": 0.8,
    "estimation_robustness": 0.8,
    "cma_utilization": 0.14823063011842744
  }
}