{
  "slug": "market-cap-weight",
  "name": "Market-Cap Weight",
  "category": "A_Heuristic",
  "method": "market_cap_weight",
  "weights": {
    "kr-large-cap": 0.10338968332921686,
    "kr-dividend": 0.10338968332921686,
    "us-large-cap": 0.2398309154182294,
    "us-tech": 0.10338968332921686,
    "kr-treasuries-10y": 0.08418385786257523,
    "us-treasuries-10y": 0.08418385786257523,
    "us-ig-credit": 0.08418385786257523,
    "gold": 0.14999999846449297,
    "kofr-cash": 0.02372423127095066,
    "money-market": 0.02372423127095066
  },
  "expected_return": 0.05533535513377713,
  "expected_vol": 0.08882227263389672,
  "metrics": {
    "ex_ante_vol": 0.08882227263389672,
    "ex_ante_var95": -0.09077728334898297,
    "backtest_sharpe": 2.4610869470709167,
    "backtest_vol": 0.10161734572712129,
    "backtest_maxdd": -0.08160234948767997,
    "hhi": 0.13447359145911494,
    "effective_n": 7.436404346380812,
    "top3": 0.4932205972119392,
    "ips_compliance": 0.9,
    "ips_flags": [
      "tracking_error=9.29% exceeds budget 6.00%"
    ],
    "tracking_error": 0.09292984798944898,
    "factor_tilts": {
      "growth": 0.4658161075433047,
      "rates": -0.8017133915869803,
      "inflation": -0.409036778550005,
      "dollar": 0.0
    },
    "diversification": 0.3552245752882528,
    "regime_fit": 0.5,
    "estimation_robustness": 0.55,
    "cma_utilization": 0.13436260614542903
  }
}