{
  "slug": "adversarial-diversifier",
  "name": "Adversarial Diversifier",
  "category": "D_NonTraditional",
  "method": "adversarial_diversifier",
  "weights": {
    "kr-large-cap": 0.06874999412675235,
    "kr-kosdaq": 0.06874999412675235,
    "kr-dividend": 0.06874999412675235,
    "us-large-cap": 0.06874999412675235,
    "us-tech": 0.06874999412675235,
    "us-dividend": 0.06874999412675235,
    "intl-developed": 0.06874999412675235,
    "emerging-markets": 0.06874999412675235,
    "kr-treasuries-10y": 0.0,
    "kr-short-bonds": 0.0014130356967920977,
    "kr-credit": 0.0,
    "us-treasuries-10y": 0.0883104740280907,
    "us-treasuries-30y": 0.0883104740280907,
    "us-ig-credit": 0.0883104740280907,
    "gold": 0.07499999895723171,
    "commodities": 0.07499999895723171,
    "kofr-cash": 0.017054461542422475,
    "money-market": 0.016601129748031136
  },
  "expected_return": 0.05428884904040637,
  "expected_vol": 0.09111311109052374,
  "metrics": {
    "ex_ante_vol": 0.09111311109052374,
    "ex_ante_var95": -0.09559221870350518,
    "backtest_sharpe": 2.206943785848926,
    "backtest_vol": 0.09960325061893159,
    "backtest_maxdd": -0.09240090528702061,
    "hhi": 0.07302716153308896,
    "effective_n": 13.693535104015993,
    "top3": 0.2649314220842721,
    "ips_compliance": 0.9,
    "ips_flags": [
      "tracking_error=8.79% exceeds budget 6.00%"
    ],
    "tracking_error": 0.08790874366215545,
    "factor_tilts": {
      "growth": 0.5366894779431599,
      "rates": -0.6514388360816039,
      "inflation": -0.1991895653824684,
      "dollar": 0.0
    },
    "diversification": 0.3174979945151749,
    "regime_fit": 0.5,
    "estimation_robustness": 0.3,
    "cma_utilization": 0.08218414577539805
  }
}